tidepredict/__init__.py
tidepredict/__main__.py
tidepredict/astro.py
tidepredict/constants.py
tidepredict/constituent.py
tidepredict/ftp_helpers.py
tidepredict/nodal_corrections.py
tidepredict/plotpng.py
tidepredict/process_station_info.py
tidepredict/process_station_list.py
tidepredict/processdata.py
tidepredict/tide.py
tidepredict/timefunc.py
tidepredict-0.4.10.dist-info/LICENSE
tidepredict-0.4.10.dist-info/METADATA
tidepredict-0.4.10.dist-info/WHEEL
tidepredict-0.4.10.dist-info/top_level.txt
tidepredict-0.4.10.dist-info/RECORD
