Metadata-Version: 2.1
Name: tidepredict
Version: 0.4.10
Summary: Tide Prediction tools
Home-page: https://github.com/windcrusader/tidepredict
Author: Brad Henderson
Author-email: ba.henderson@gmail.com
License: MIT
Classifier: License :: OSI Approved :: MIT License
Classifier: Programming Language :: Python :: 3
Classifier: Programming Language :: Python :: 3.7
Requires-Python: >=3.5
License-File: LICENSE
Requires-Dist: numpy
Requires-Dist: matplotlib
Requires-Dist: pandas
Requires-Dist: jinja2
Requires-Dist: scipy
Requires-Dist: timezonefinder
